{
  "projects": [
    {
      "id": 1,
      "projectName": "CodeStreaks",
      "projectDescription": "test description",
      "posts": [
        {
          "id": 1,
          "postDate": "Wed Mar 25 2020 11:01:01 GMT-0300 (Brasilia Standard Time)",
          "postTitle": "Improved styling and added new methods",
          "postContent": "Hurried day today! I was able to find some time later in the day and take a look at that navbar that was bothering me. Lots of progress there! Also, I’ve added some new links in the homepage. Will take a better look at it tomorrow."
        },
        {
          "id": 2,
          "postDate": "Wed Mar 24 2020 11:01:01 GMT-0300 (Brasilia Standard Time)",
          "postTitle": "Did some stuff",
          "postContent": "Hurried day today! I was able to find some time later in the day and take a look at that navbar that was bothering me. Lots of progress there! Also, I’ve added some new links in the homepage. Will take a better look at it tomorrow."
        }
      ]
    },
    {
      "id": 2,
      "projectName": "Test project",
      "projectDescription": "test description",
      "posts": [
        {
          "id": 3,
          "postDate": "Wed Mar 23 2020 11:01:01 GMT-0300 (Brasilia Standard Time)",
          "postTitle": "Added git repository",
          "postContent": "Hurried day today! I was able to find some time later in the day and take a look at that navbar that was bothering me. Lots of progress there! Also, I’ve added some new links in the homepage. Will take a better look at it tomorrow."
        },
        {
          "id": 4,
          "postDate": "Wed Mar 22 2020 11:01:01 GMT-0300 (Brasilia Standard Time)",
          "postTitle": "Started project",
          "postContent": "Hurried day today! I was able to find some time later in the day and take a look at that navbar that was bothering me. Lots of progress there! Also, I’ve added some new links in the homepage. Will take a better look at it tomorrow."
        },
        {
          "id": 5,
          "postDate": "Wed Mar 24 2020 11:01:01 GMT-0300 (Brasilia Standard Time)",
          "postTitle": "Started project",
          "postContent": "Hurried day today! I was able to find some time later in the day and take a look at that navbar that was bothering me. Lots of progress there! Also, I’ve added some new links in the homepage. Will take a better look at it tomorrow."
        }
      ]
    }
  ]
}